json_lxml.py
setup.py
json_lxml.egg-info/PKG-INFO
json_lxml.egg-info/SOURCES.txt
json_lxml.egg-info/dependency_links.txt
json_lxml.egg-info/requires.txt
json_lxml.egg-info/top_level.txt