Metadata-Version: 1.0
Name: json-lxml
Version: 0.1.3
Summary: Convert JSON to lxml.etree so that xpath can be applied.
Home-page: https://github.com/tengu/py-json-lxml
Author: karasuyamatengu
Author-email: karasuyamatengu@gmail.com
License: LGPL
Keywords: json,xpath,lxml
Platform: POSIX
Platform: Windows
Classifier: License :: OSI Approved :: GNU Library or Lesser General Public License (LGPL)
Classifier: Operating System :: POSIX :: Linux
Classifier: Programming Language :: Python
Classifier: Development Status :: 4 - Beta
Classifier: Environment :: Console
Classifier: Intended Audience :: Developers
Classifier: Topic :: Utilities
